astrodb_utils/__init__.py
astrodb_utils/fits.py
astrodb_utils/instruments.py
astrodb_utils/loaders.py
astrodb_utils/photometry.py
astrodb_utils/publications.py
astrodb_utils/sources.py
astrodb_utils/spectra.py
astrodb_utils/utils.py
astrodb_utils/version.py
astrodb_utils-1.2.dist-info/licenses/LICENSE
astrodb_utils-1.2.dist-info/METADATA
astrodb_utils-1.2.dist-info/WHEEL
astrodb_utils-1.2.dist-info/entry_points.txt
astrodb_utils-1.2.dist-info/top_level.txt
astrodb_utils-1.2.dist-info/RECORD
