Metadata-Version: 2.4
Name: astrodb_utils
Version: 1.2
Summary: astrodb_utils: scripts for interacting with the astrodb database
Author: Kelle Cruz, David Rodriguez
Author-email: Arjun Savel <asavel@umd.edu>
License-Expression: BSD-3-Clause
Project-URL: Homepage, https://github.com/astrodbtoolkit/astrodb_utils
Project-URL: Issues, https://github.com/astrodbtoolkit/astrodb_utils/issues
Project-URL: Documentation, https://astrodb-utils.readthedocs.io/en/latest/
Keywords: databases,astronomy
Classifier: Programming Language :: Python :: 3
Requires-Python: >=3.11
License-File: LICENSE
Requires-Dist: numpy<3.0
Requires-Dist: astroquery>=0.4.9
Requires-Dist: astropy>7.0
Requires-Dist: astrodbkit>=2.5
Requires-Dist: lsst-felis
Requires-Dist: pandas
Requires-Dist: tqdm
Requires-Dist: ads>=0.12.7
Requires-Dist: dateparser
Requires-Dist: specutils>=2.2
Provides-Extra: test
Requires-Dist: pytest; extra == "test"
Requires-Dist: ruff>0.3.7; extra == "test"
Requires-Dist: pre-commit; extra == "test"
Requires-Dist: pytest-dependency; extra == "test"
Requires-Dist: gitpython; extra == "test"
Provides-Extra: docs
Requires-Dist: sphinx; extra == "docs"
Requires-Dist: sphinx-autobuild; extra == "docs"
Requires-Dist: sphinx_pyproject; extra == "docs"
Requires-Dist: nbsphinx; extra == "docs"
Requires-Dist: pydata-sphinx-theme; extra == "docs"
Requires-Dist: pandoc; extra == "docs"
Requires-Dist: sphinx_mdinclude; extra == "docs"
Requires-Dist: doc8; extra == "docs"
Provides-Extra: all
Requires-Dist: astrodb_utils[docs,test]; extra == "all"
Dynamic: license-file
